aiomanhole/__init__.py
aiomanhole-0.7.0.dist-info/LICENSE
aiomanhole-0.7.0.dist-info/METADATA
aiomanhole-0.7.0.dist-info/WHEEL
aiomanhole-0.7.0.dist-info/top_level.txt
aiomanhole-0.7.0.dist-info/RECORD
