Metadata-Version: 2.1
Name: aiomanhole
Version: 0.7.0
Summary: Python module to provide a manhole in asyncio applications
Home-page: https://github.com/nathan-hoad/aiomanhole
Author: Nathan Hoad
Author-email: nathan@hoad.io
License: BSD (3-clause)
Platform: UNKNOWN
Classifier: Intended Audience :: Developers
Classifier: Natural Language :: English
Classifier: License :: OSI Approved :: BSD License
Classifier: Programming Language :: Python :: 3
Classifier: Programming Language :: Python :: 3.6
Classifier: Programming Language :: Python :: 3.7
Classifier: Programming Language :: Python :: 3.8
Classifier: Programming Language :: Python :: 3.9
Classifier: Programming Language :: Python :: 3.10
License-File: LICENSE
